pymvr/__init__.py
pymvr/value.py
pymvr-1.0.6.dist-info/licenses/LICENSE
pymvr-1.0.6.dist-info/METADATA
pymvr-1.0.6.dist-info/WHEEL
pymvr-1.0.6.dist-info/top_level.txt
pymvr-1.0.6.dist-info/RECORD
