Metadata-Version: 2.4
Name: pymvr
Version: 1.0.6
Summary: My Virtual Rig (MVR) library for Python
Author-email: vanous <noreply@nodomain.com>
Maintainer-email: vanous <noreply@nodomain.com>
Project-URL: Repository, https://github.com/open-stage/python-mvr.git
Project-URL: Changelog, https://github.com/open-stage/python-mvr/blob/master/CHANGELOG.md
Keywords: MVR,GDTF
Classifier: Development Status :: 4 - Beta
Classifier: Programming Language :: Python
Requires-Python: >=3.8
License-File: LICENSE
Dynamic: license-file
